MANIFEST.in
README.rst
setup.py
bin/pipelines
pipelines/__init__.py
pipelines/utils.py
pipelines.egg-info/PKG-INFO
pipelines.egg-info/SOURCES.txt
pipelines.egg-info/dependency_links.txt
pipelines.egg-info/requires.txt
pipelines.egg-info/top_level.txt
pipelines/api/__init__.py
pipelines/api/ghauth.py
pipelines/api/server.py
pipelines/api/app_dist/index.html
pipelines/api/app_dist/client/dist/bundle.min.js
pipelines/api/templates/login.html
pipelines/pipeline/__init__.py
pipelines/pipeline/exceptions.py
pipelines/pipeline/pipeline.py
pipelines/pipeline/task.py
pipelines/pipeline/utils.py
pipelines/pipeline/var_processing.py
pipelines/plugin/__init__.py
pipelines/plugin/base_plugin.py
pipelines/plugin/exceptions.py
pipelines/plugin/manager.py
pipelines/plugin/utils.py
pipelines/plugins/__init__.py
pipelines/plugins/base_executor.py
pipelines/plugins/bash_executor.py
pipelines/plugins/dummy_executor.py
pipelines/plugins/file_logger.py
pipelines/plugins/python_executor.py
pipelines/plugins/slack_executor.py
pipelines/plugins/status_logger.py
pipelines/plugins/stdout_logger.py
pipelines/plugins/webhook_logger.py