Metadata-Version: 1.0
Name: pipelines
Version: 0.0.14
Summary: Pipelines
Home-page: https://getpipelines.com
Author: Wiredcraft
Author-email: info@wiredcraft.com
License: MIT
Platform: UNKNOWN
